shwim/__init__.py
shwim/__init__.py~
shwim/cli.py
shwim/cli.py~
shwim/status.py
shwim/status.py~
shwim-25.9.0.dist-info/METADATA
shwim-25.9.0.dist-info/WHEEL
shwim-25.9.0.dist-info/entry_points.txt
shwim-25.9.0.dist-info/licenses/LICENSE
shwim-25.9.0.dist-info/RECORD
