Metadata-Version: 2.4
Name: shwim
Version: 25.9.0
Summary: Encrypted, peer-to-peer terminal sharing for two people.
Author-email: meejah <meejah@meejah.ca>
License: The MIT License (MIT)
License-File: LICENSE
Keywords: fowl,magic-wormhole
Classifier: Framework :: Twisted
Classifier: License :: OSI Approved :: MIT License
Classifier: Programming Language :: Python :: 3
Requires-Python: >=3.10
Requires-Dist: fowl>=25.7.0
Requires-Dist: magic-wormhole>=0.20.0
Provides-Extra: dev
Requires-Dist: cuvner; extra == 'dev'
Requires-Dist: dulwich; extra == 'dev'
Requires-Dist: gpg; extra == 'dev'
Requires-Dist: hatch; extra == 'dev'
Requires-Dist: pip-tools; extra == 'dev'
Requires-Dist: readme-renderer; extra == 'dev'
Requires-Dist: sphinx; extra == 'dev'
Requires-Dist: twine; extra == 'dev'
Provides-Extra: test
Requires-Dist: pytest; extra == 'test'
